<?xml version="1.0" encoding="UTF-8"?>
<!DOCTYPE suite SYSTEM "https://testng.org/testng-1.0.dtd">
<suite name="Suite">
  <test thread-count="5" name="Test">
	  <parameter name="Url" value="https://naveenautomationlabs.com/opencart/"></parameter>
	  <parameter name="User" value="kavithayelisetti19@gmail.com"></parameter>
	  <parameter name="Pwd" value="llchinna"></parameter>
    <classes>
      <class name="packOne.Parameter">
		  
	  </class>
    </classes>
  </test> <!-- Test -->
</suite> <!-- Suite -->
